dpayocr/__init__.py
dpayocr/payqrcode.py
dpayocr-1.0.2.data/scripts/payqrcode.py
dpayocr-1.0.2.dist-info/METADATA
dpayocr-1.0.2.dist-info/WHEEL
dpayocr-1.0.2.dist-info/entry_points.txt
dpayocr-1.0.2.dist-info/top_level.txt
dpayocr-1.0.2.dist-info/RECORD
