Metadata-Version: 2.1
Name: dpayocr
Version: 1.0.2
Summary: 识别支付宝微信收款码信息
Home-page: https://github.com/dust8/dpayocr
License: UNKNOWN
Platform: UNKNOWN
Classifier: Programming Language :: Python :: 3
Classifier: License :: OSI Approved :: MIT License
Requires-Python: >=3.7
Requires-Dist: pillow
Requires-Dist: pytesseract
Requires-Dist: pyzbar
